docling_ocr/__init__.py
docling_ocr/extractors.py
docling_ocr/utils.py
docling_ocr/version.py
docling_ocr-0.1.0.dist-info/licenses/LICENSE
docling_ocr-0.1.0.dist-info/METADATA
docling_ocr-0.1.0.dist-info/WHEEL
docling_ocr-0.1.0.dist-info/top_level.txt
docling_ocr-0.1.0.dist-info/RECORD
