Metadata-Version: 2.4
Name: docling_ocr
Version: 0.1.0
Summary: An OCR package using LLM models for text extraction from images
Home-page: https://github.com/FREDERICO23/docling_ocr
Author: Adhing'a Fredrick
Author-email: adhingafredrick@gmail.com
Classifier: Programming Language :: Python :: 3
Classifier: License :: OSI Approved :: MIT License
Classifier: Operating System :: OS Independent
Requires-Python: >=3.7
License-File: LICENSE
Requires-Dist: torch>=1.10.0
Requires-Dist: transformers>=4.15.0
Requires-Dist: Pillow>=8.0.0
Dynamic: author
Dynamic: author-email
Dynamic: classifier
Dynamic: description
Dynamic: description-content-type
Dynamic: home-page
Dynamic: license-file
Dynamic: requires-dist
Dynamic: requires-python
Dynamic: summary
